{
	"__inputs": [{
		"name": "DS_PROMETHEUS",
		"label": "Prometheus",
		"description": "",
		"type": "datasource",
		"pluginId": "prometheus",
		"pluginName": "Prometheus"
	}],
	"__requires": [{
			"type": "grafana",
			"id": "grafana",
			"name": "Grafana",
			"version": "4.2.0"
		},
		{
			"type": "panel",
			"id": "graph",
			"name": "Graph",
			"version": ""
		},
		{
			"type": "datasource",
			"id": "prometheus",
			"name": "Prometheus",
			"version": "1.0.0"
		},
		{
			"type": "panel",
			"id": "singlestat",
			"name": "Singlestat",
			"version": ""
		}
	],
	"annotations": {
		"list": []
	},
	"editable": true,
	"gnetId": 2121,
	"graphTooltip": 0,
	"hideControls": false,
	"id": null,
	"links": [],
	"refresh": "10s",
	"rows": [{
		"collapse": false,
		"height": 266,
		"panels": [{
				"aliasColors": {},
				"bars": false,
				"dashLength": 10,
				"dashes": false,
				"datasource": "Prometheus",
				"decimals": 0,
				"fill": 1,
				"gridPos": {
					"h": 7,
					"w": 6,
					"x": 0,
					"y": 0
				},
				"id": 6,
				"legend": {
					"alignAsTable": true,
					"avg": false,
					"current": false,
					"max": false,
					"min": false,
					"show": true,
					"total": false,
					"values": false
				},
				"lines": true,
				"linewidth": 1,
				"links": [],
				"nullPointMode": "null",
				"percentage": false,
				"pointradius": 5,
				"points": false,
				"renderer": "flot",
				"seriesOverrides": [],
				"spaceLength": 10,
				"stack": false,
				"steppedLine": false,
				"targets": [{
					"expr": "fastdfs_group_count",
					"format": "time_series",
					"intervalFactor": 2,
					"legendFormat": "fastdfs_group_count",
					"metric": "fastdfs_group_count",
					"refId": "A",
					"step": 2
				}],
				"thresholds": [],
				"timeFrom": null,
				"timeShift": null,
				"title": "GroupCount",
				"tooltip": {
					"shared": true,
					"sort": 0,
					"value_type": "individual"
				},
				"type": "graph",
				"xaxis": {
					"buckets": null,
					"mode": "time",
					"name": null,
					"show": true,
					"values": []
				},
				"yaxes": [{
						"format": "short",
						"label": null,
						"logBase": 1,
						"max": null,
						"min": null,
						"show": true
					},
					{
						"format": "short",
						"label": null,
						"logBase": 1,
						"max": null,
						"min": null,
						"show": true
					}
				]
			},
			{
				"aliasColors": {},
				"bars": false,
				"dashLength": 10,
				"dashes": false,
				"datasource": "Prometheus",
				"decimals": 0,
				"fill": 1,
				"gridPos": {
					"h": 7,
					"w": 6,
					"x": 6,
					"y": 0
				},
				"id": 7,
				"legend": {
					"alignAsTable": true,
					"avg": false,
					"current": false,
					"max": false,
					"min": false,
					"show": true,
					"total": false,
					"values": false
				},
				"lines": true,
				"linewidth": 1,
				"links": [],
				"nullPointMode": "null",
				"percentage": false,
				"pointradius": 5,
				"points": false,
				"renderer": "flot",
				"seriesOverrides": [],
				"spaceLength": 10,
				"stack": false,
				"steppedLine": false,
				"targets": [{
					"expr": "fastdfs_active_state",
					"format": "time_series",
					"intervalFactor": 2,
					"legendFormat": "fastdfs_active_state",
					"metric": "fastdfs_active_state",
					"refId": "A",
					"step": 2
				}],
				"thresholds": [],
				"timeFrom": null,
				"timeShift": null,
				"title": "Active",
				"tooltip": {
					"shared": true,
					"sort": 0,
					"value_type": "individual"
				},
				"type": "graph",
				"xaxis": {
					"buckets": null,
					"mode": "time",
					"name": null,
					"show": true,
					"values": []
				},
				"yaxes": [{
						"format": "short",
						"label": null,
						"logBase": 1,
						"max": null,
						"min": null,
						"show": true
					},
					{
						"format": "short",
						"label": null,
						"logBase": 1,
						"max": null,
						"min": null,
						"show": true
					}
				]
			},
			{
				"aliasColors": {},
				"bars": false,
				"dashLength": 10,
				"dashes": false,
				"datasource": "Prometheus",
				"decimals": 0,
				"fill": 1,
				"gridPos": {
					"h": 7,
					"w": 6,
					"x": 12,
					"y": 0
				},
				"id": 8,
				"legend": {
					"alignAsTable": true,
					"avg": false,
					"current": false,
					"max": false,
					"min": false,
					"show": true,
					"total": false,
					"values": false
				},
				"lines": true,
				"linewidth": 1,
				"links": [],
				"nullPointMode": "null",
				"percentage": false,
				"pointradius": 5,
				"points": false,
				"renderer": "flot",
				"seriesOverrides": [],
				"spaceLength": 10,
				"stack": false,
				"steppedLine": false,
				"targets": [{
					"expr": "fastdfs_wait_sync_state",
					"format": "time_series",
					"intervalFactor": 2,
					"legendFormat": "fastdfs_wait_sync_state",
					"metric": "fastdfs_wait_sync_state",
					"refId": "A",
					"step": 2
				}],
				"thresholds": [],
				"timeFrom": null,
				"timeShift": null,
				"title": "WaitSync",
				"tooltip": {
					"shared": true,
					"sort": 0,
					"value_type": "individual"
				},
				"type": "graph",
				"xaxis": {
					"buckets": null,
					"mode": "time",
					"name": null,
					"show": true,
					"values": []
				},
				"yaxes": [{
						"format": "short",
						"label": null,
						"logBase": 1,
						"max": null,
						"min": null,
						"show": true
					},
					{
						"format": "short",
						"label": null,
						"logBase": 1,
						"max": null,
						"min": null,
						"show": true
					}
				]
			},
			{
				"aliasColors": {},
				"bars": false,
				"dashLength": 10,
				"dashes": false,
				"datasource": "Prometheus",
				"decimals": 0,
				"fill": 1,
				"gridPos": {
					"h": 7,
					"w": 6,
					"x": 18,
					"y": 0
				},
				"id": 9,
				"legend": {
					"alignAsTable": true,
					"avg": false,
					"current": false,
					"max": false,
					"min": false,
					"show": true,
					"total": false,
					"values": false
				},
				"lines": true,
				"linewidth": 1,
				"links": [],
				"nullPointMode": "null",
				"percentage": false,
				"pointradius": 5,
				"points": false,
				"renderer": "flot",
				"seriesOverrides": [],
				"spaceLength": 10,
				"stack": false,
				"steppedLine": false,
				"targets": [{
					"expr": "fastdfs_wait_sync_state{node=\"fastdfs\"} + on(node) fastdfs_active_state{node=\"fastdfs\"}",
					"format": "time_series",
					"intervalFactor": 2,
					"legendFormat": "alive",
					"metric": "fastdfs_alive",
					"refId": "A",
					"step": 2
				}],
				"thresholds": [],
				"timeFrom": null,
				"timeShift": null,
				"title": "Alive",
				"tooltip": {
					"shared": true,
					"sort": 0,
					"value_type": "individual"
				},
				"type": "graph",
				"xaxis": {
					"buckets": null,
					"mode": "time",
					"name": null,
					"show": true,
					"values": []
				},
				"yaxes": [{
						"format": "short",
						"label": null,
						"logBase": 1,
						"max": null,
						"min": null,
						"show": true
					},
					{
						"format": "short",
						"label": null,
						"logBase": 1,
						"max": null,
						"min": null,
						"show": true
					}
				]
			},
			{
				"aliasColors": {},
				"bars": true,
				"dashLength": 10,
				"dashes": false,
				"datasource": "Prometheus",
				"decimals": 0,
				"fill": 1,
				"gridPos": {
				  "h": 7,
				  "w": 8,
				  "x": 8,
				  "y": 7
				},
				"id": 10,
				"legend": {
				  "alignAsTable": false,
				  "avg": false,
				  "current": false,
				  "max": false,
				  "min": false,
				  "show": false,
				  "total": false,
				  "values": false
				},
				"lines": false,
				"linewidth": 1,
				"links": [],
				"nullPointMode": "null",
				"percentage": false,
				"pointradius": 5,
				"points": false,
				"renderer": "flot",
				"seriesOverrides": [],
				"spaceLength": 10,
				"stack": false,
				"steppedLine": false,
				"targets": [
				  {
					"$$hashKey": "object:142",
					"expr": "fastdfs_config_group_count",
					"format": "time_series",
					"instant": false,
					"intervalFactor": 1,
					"legendFormat": "config_group_count",
					"metric": "fastdfs_alive",
					"refId": "A",
					"step": 2
				  },
				  {
					"$$hashKey": "object:163",
					"expr": "fastdfs_config_storage_num",
					"format": "time_series",
					"instant": false,
					"intervalFactor": 1,
					"legendFormat": "config_storage_num",
					"refId": "B"
				  }
				],
				"thresholds": [],
				"timeFrom": null,
				"timeShift": null,
				"title": "Config",
				"tooltip": {
				  "shared": false,
				  "sort": 0,
				  "value_type": "individual"
				},
				"transparent": false,
				"type": "graph",
				"xaxis": {
				  "buckets": null,
				  "mode": "series",
				  "name": null,
				  "show": true,
				  "values": [
					"current"
				  ]
				},
				"yaxes": [
				  {
					"$$hashKey": "object:188",
					"format": "short",
					"label": null,
					"logBase": 1,
					"max": null,
					"min": null,
					"show": true
				  },
				  {
					"$$hashKey": "object:189",
					"format": "short",
					"label": null,
					"logBase": 1,
					"max": null,
					"min": null,
					"show": true
				  }
				]
			  }
		],
		"refresh": "5s",
		"schemaVersion": 16,
		"style": "dark",
		"tags": [],
		"templating": {
			"list": [{
				"current": {
					"text": "Prometheus",
					"value": "Prometheus"
				},
				"hide": 0,
				"label": null,
				"name": "datasource",
				"options": [],
				"query": "prometheus",
				"refresh": 1,
				"regex": "",
				"type": "datasource"
			}]
		},
		"time": {
			"from": "now-5m",
			"to": "now"
		},
		"timepicker": {
			"refresh_intervals": [
				"5s",
				"10s",
				"30s",
				"1m",
				"5m",
				"15m",
				"30m",
				"1h",
				"2h",
				"1d"
			],
			"time_options": [
				"5m",
				"15m",
				"1h",
				"6h",
				"12h",
				"24h",
				"2d",
				"7d",
				"30d"
			]
		},
		"timezone": "browser",
		"description": "Dashboard for FastDFS.",
		"title": "FastDFS",
		"version": 1
	}]
}